pypollencom/__init__.py
pypollencom/__version__.py
pypollencom/allergens.py
pypollencom/asthma.py
pypollencom/client.py
pypollencom/decorators.py
pypollencom/disease.py
pypollencom/errors.py
tests/fixtures/__init__.py
tests/fixtures/allergens.py
tests/fixtures/asthma.py
tests/fixtures/disease.py
pypollencom-2.2.4.dist-info/AUTHORS.md
pypollencom-2.2.4.dist-info/LICENSE
pypollencom-2.2.4.dist-info/METADATA
pypollencom-2.2.4.dist-info/WHEEL
pypollencom-2.2.4.dist-info/top_level.txt
pypollencom-2.2.4.dist-info/RECORD
