Metadata-Version: 2.1
Name: pypollencom
Version: 2.2.4
Summary: A simple API for Pollen.com data
Home-page: https://github.com/bachya/pypollencom
Author: Aaron Bach
Author-email: bachya1208@gmail.com
License: MIT
Platform: UNKNOWN
Classifier: License :: OSI Approved :: MIT License
Classifier: Programming Language :: Python
Classifier: Programming Language :: Python :: 3
Classifier: Programming Language :: Python :: 3.5
Classifier: Programming Language :: Python :: 3.6
Classifier: Programming Language :: Python :: 3.7
Classifier: Programming Language :: Python :: Implementation :: CPython
Classifier: Programming Language :: Python :: Implementation :: PyPy
Requires-Python: >=3.5.3
Requires-Dist: aiohttp
